noisyopt/__init__.py
noisyopt/main.py
noisyopt/version.py
noisyopt/tests/__init__.py
noisyopt/tests/test_noisyopt.py
noisyopt-0.2.3.dist-info/licenses/LICENSE
noisyopt-0.2.3.dist-info/METADATA
noisyopt-0.2.3.dist-info/WHEEL
noisyopt-0.2.3.dist-info/top_level.txt
noisyopt-0.2.3.dist-info/RECORD
